cubicweb_invoice/__init__.py
cubicweb_invoice/__pkginfo__.py
cubicweb_invoice/entities.py
cubicweb_invoice/schema.py
cubicweb_invoice/sobjects.py
cubicweb_invoice/views.py
cubicweb_invoice/i18n/en.po
cubicweb_invoice/i18n/es.po
cubicweb_invoice/i18n/fr.po
cubicweb_invoice/migration/0.2.0_Any.py
cubicweb_invoice/migration/0.3.1_Any.py
cubicweb_invoice/migration/0.8.0_Any.py
cubicweb_invoice/migration/postcreate.py
cubicweb_invoice-1.1.0.dist-info/METADATA
cubicweb_invoice-1.1.0.dist-info/WHEEL
cubicweb_invoice-1.1.0.dist-info/entry_points.txt
cubicweb_invoice-1.1.0.dist-info/top_level.txt
cubicweb_invoice-1.1.0.dist-info/RECORD
